<?xml version="1.0" encoding="utf-8"?>
<HarvestingProgramDetailsList>
  <PlotList plotNo="15463">
    <ProgramNo>1</ProgramNo>
    <GrowerCode>47029</GrowerCode>
    <GrowerName>भोईटे दत्तात्रय आनंदराव</GrowerName>
    <GatCode>34</GatCode>
    <GatName>फलटण</GatName>
    <VillageCode>1299</VillageCode>
    <VillageName>हिंगणगाव (फलटण)</VillageName>
    <serveNo>-</serveNo>
    <CaneVariety>2</CaneVariety>
    <CaneVarietyName>CoM-265</CaneVarietyName>
    <CaneCode>पु.हंगामी</CaneCode>
    <CanegrowerType>बिगर सभासद</CanegrowerType>
    <Irrigation>विहीर</Irrigation>
    <Plotend>N</Plotend>
  </PlotList>
  <PlotList plotNo="15618">
    <ProgramNo>1</ProgramNo>
    <GrowerCode>47111</GrowerCode>
    <GrowerName>भोईटे गौरी अंकुश </GrowerName>
    <GatCode>34</GatCode>
    <GatName>फलटण</GatName>
    <VillageCode>1299</VillageCode>
    <VillageName>हिंगणगाव (फलटण)</VillageName>
    <serveNo>-</serveNo>
    <CaneVariety>2</CaneVariety>
    <CaneVarietyName>CoM-265</CaneVarietyName>
    <CaneCode>पु.हंगामी</CaneCode>
    <CanegrowerType>बिगर सभासद</CanegrowerType>
    <Irrigation>विहीर</Irrigation>
    <Plotend>N</Plotend>
  </PlotList>
  <PlotList plotNo="15565">
    <ProgramNo>1</ProgramNo>
    <GrowerCode>47086</GrowerCode>
    <GrowerName>भोईटे सुरेश आनंदराव</GrowerName>
    <GatCode>34</GatCode>
    <GatName>फलटण</GatName>
    <VillageCode>1299</VillageCode>
    <VillageName>हिंगणगाव (फलटण)</VillageName>
    <serveNo>-</serveNo>
    <CaneVariety>2</CaneVariety>
    <CaneVarietyName>CoM-265</CaneVarietyName>
    <CaneCode>पु.हंगामी</CaneCode>
    <CanegrowerType>बिगर सभासद</CanegrowerType>
    <Irrigation>विहीर</Irrigation>
    <Plotend>N</Plotend>
  </PlotList>
  <PlotList plotNo="15889">
    <ProgramNo>1</ProgramNo>
    <GrowerCode>47271</GrowerCode>
    <GrowerName>भोईटे ज्ञानदेव नारायण</GrowerName>
    <GatCode>34</GatCode>
    <GatName>फलटण</GatName>
    <VillageCode>1299</VillageCode>
    <VillageName>हिंगणगाव (फलटण)</VillageName>
    <serveNo>-</serveNo>
    <CaneVariety>2</CaneVariety>
    <CaneVarietyName>CoM-265</CaneVarietyName>
    <CaneCode>पु.हंगामी</CaneCode>
    <CanegrowerType>बिगर सभासद</CanegrowerType>
    <Irrigation>विहीर</Irrigation>
    <Plotend>N</Plotend>
  </PlotList>
  <PlotList plotNo="15440">
    <ProgramNo>1</ProgramNo>
    <GrowerCode>47021</GrowerCode>
    <GrowerName>भोईटे जयवंत आनंदराव</GrowerName>
    <GatCode>34</GatCode>
    <GatName>फलटण</GatName>
    <VillageCode>1299</VillageCode>
    <VillageName>हिंगणगाव (फलटण)</VillageName>
    <serveNo>-</serveNo>
    <CaneVariety>2</CaneVariety>
    <CaneVarietyName>CoM-265</CaneVarietyName>
    <CaneCode>पु.हंगामी</CaneCode>
    <CanegrowerType>बिगर सभासद</CanegrowerType>
    <Irrigation>विहीर</Irrigation>
    <Plotend>N</Plotend>
  </PlotList>
</HarvestingProgramDetailsList>